{
  "project": "violet-vault",
  "lastUpdated": "2025-09-30",
  "currentStatus": {
    "totalErrors": 0,
    "targetErrors": 0
  },
  "errorCategories": [],
  "actionPlan": {
    "highPriority": [],
    "mediumPriority": [],
    "lowPriority": []
  },
  "commands": {
    "checkTypes": "npm run tsc:check",
    "watchTypes": "npm run tsc:watch",
    "checkSpecificFile": "npx tsc --noEmit src/path/to/file.ts"
  },
  "monitoring": {
    "target": "0 type errors",
    "reviewFrequency": "On every PR",
    "autoCheck": "Automated via GitHub Actions"
  }
}
